xontrib/z.py
xontrib_z-0.4.dist-info/METADATA
xontrib_z-0.4.dist-info/RECORD
xontrib_z-0.4.dist-info/WHEEL
xontrib_z-0.4.dist-info/top_level.txt
