Metadata-Version: 2.1
Name: xontrib-z
Version: 0.4
Summary: Tracks your most used directories, based on 'frecency'.
Home-page: https://github.com/astronouth7303/xontrib-z
Author: Jamie Bliss
Author-email: astronouth7303@gmail.com
License: GPLv3
Platform: any
Classifier: Environment :: Console
Classifier: Intended Audience :: End Users/Desktop
Classifier: Operating System :: OS Independent
Classifier: Programming Language :: Python
Classifier: Topic :: Desktop Environment
Classifier: Topic :: System :: Shells
Classifier: Topic :: System :: System Shells
